{
  "version": "1.0",
  "categoryId": 8013,
  "lastUpdated": "2025-04-06T06:06:01.523Z",
  "skills": {
    "130100": {
      "id": 130100,
      "type": "switch",
      "templateId": 10908,
      "name": "Popori_M_Elementalist_Lv01_Critical Up Aura_On 01",
      "category": [
        8013,
        19,
        107,
        10000,
        9999
      ],
      "timeRate": 1.1,
      "totalAtk": 0,
      "class": "mystic",
      "animationDuration": 0,
      "pendingStartTime": 350,
      "coolTime": 2000,
      "mpCost": 375,
      "hpCost": 0,
      "nextSkill": 130150,
      "movable": false,
      "stages": []
    },
    "130150": {
      "id": 130150,
      "type": "switch",
      "templateId": 10908,
      "name": "Popori_M_Elementalist_Lv01_Critical Up Aura_Off 01",
      "category": [
        8013,
        19,
        107,
        10001,
        9999
      ],
      "timeRate": 1.1,
      "totalAtk": 0,
      "class": "mystic",
      "animationDuration": 0,
      "pendingStartTime": 350,
      "coolTime": 0,
      "mpCost": 0,
      "hpCost": 0,
      "nextSkill": 130100,
      "movable": false,
      "stages": []
    },
    "130200": {
      "id": 130200,
      "type": "switch",
      "templateId": 10908,
      "name": "Popori_M_Elementalist_Lv02_Critical Up Aura_On 01",
      "category": [
        8013,
        19,
        107,
        10000,
        9999
      ],
      "timeRate": 1.1,
      "totalAtk": 0,
      "class": "mystic",
      "animationDuration": 0,
      "pendingStartTime": 350,
      "coolTime": 2000,
      "mpCost": 375,
      "hpCost": 0,
      "nextSkill": 130250,
      "movable": false,
      "stages": []
    },
    "130250": {
      "id": 130250,
      "type": "switch",
      "templateId": 10908,
      "name": "Popori_M_Elementalist_Lv02_Critical Up Aura_Off 01",
      "category": [
        8013,
        19,
        107,
        10001,
        9999
      ],
      "timeRate": 1.1,
      "totalAtk": 0,
      "class": "mystic",
      "animationDuration": 0,
      "pendingStartTime": 350,
      "coolTime": 0,
      "mpCost": 0,
      "hpCost": 0,
      "nextSkill": 130200,
      "movable": false,
      "stages": []
    },
    "130300": {
      "id": 130300,
      "type": "switch",
      "templateId": 10908,
      "name": "Popori_M_Elementalist_Lv03_Critical Up Aura_On 01",
      "category": [
        8013,
        19,
        107,
        10000,
        9999
      ],
      "timeRate": 1.1,
      "totalAtk": 0,
      "class": "mystic",
      "animationDuration": 0,
      "pendingStartTime": 350,
      "coolTime": 500,
      "mpCost": 50,
      "hpCost": 0,
      "nextSkill": 130350,
      "movable": false,
      "stages": []
    },
    "130350": {
      "id": 130350,
      "type": "switch",
      "templateId": 10908,
      "name": "Popori_M_Elementalist_Lv03_Critical Up Aura_Off 01",
      "category": [
        8013,
        19,
        107,
        10001,
        9999
      ],
      "timeRate": 1.1,
      "totalAtk": 0,
      "class": "mystic",
      "animationDuration": 0,
      "pendingStartTime": 350,
      "coolTime": 0,
      "mpCost": 0,
      "hpCost": 0,
      "nextSkill": 130300,
      "movable": false,
      "stages": []
    },
    "130400": {
      "id": 130400,
      "type": "switch",
      "templateId": 10908,
      "name": "Popori_M_Elementalist_Lv04_Critical Up Aura_On 01",
      "category": [
        8013,
        19,
        107,
        10000,
        9999
      ],
      "timeRate": 1.1,
      "totalAtk": 0,
      "class": "mystic",
      "animationDuration": 0,
      "pendingStartTime": 350,
      "coolTime": 500,
      "mpCost": 50,
      "hpCost": 0,
      "nextSkill": 130450,
      "movable": false,
      "stages": []
    },
    "130450": {
      "id": 130450,
      "type": "switch",
      "templateId": 10908,
      "name": "Popori_M_Elementalist_Lv04_Critical Up Aura_Off 01",
      "category": [
        8013,
        19,
        107,
        10001,
        9999
      ],
      "timeRate": 1.1,
      "totalAtk": 0,
      "class": "mystic",
      "animationDuration": 0,
      "pendingStartTime": 350,
      "coolTime": 0,
      "mpCost": 0,
      "hpCost": 0,
      "nextSkill": 130400,
      "movable": false,
      "stages": []
    },
    "130500": {
      "id": 130500,
      "type": "switch",
      "templateId": 10908,
      "name": "Popori_M_Elementalist_Lv05_Critical Up Aura_On 01",
      "category": [
        8013,
        19,
        107,
        10000,
        9999
      ],
      "timeRate": 1.1,
      "totalAtk": 0,
      "class": "mystic",
      "animationDuration": 0,
      "pendingStartTime": 350,
      "coolTime": 500,
      "mpCost": 50,
      "hpCost": 0,
      "nextSkill": 130550,
      "movable": false,
      "stages": []
    },
    "130550": {
      "id": 130550,
      "type": "switch",
      "templateId": 10908,
      "name": "Popori_M_Elementalist_Lv05_Critical Up Aura_Off 01",
      "category": [
        8013,
        19,
        107,
        10001,
        9999
      ],
      "timeRate": 1.1,
      "totalAtk": 0,
      "class": "mystic",
      "animationDuration": 0,
      "pendingStartTime": 350,
      "coolTime": 0,
      "mpCost": 0,
      "hpCost": 0,
      "nextSkill": 130500,
      "movable": false,
      "stages": []
    }
  }
}